Metadata-Version: 2.1
Name: lyricFind
Version: 0.1.0
Summary: Simplest find a lyric of the song just type part of the lyric that make your life easier
Author: Reza
Author-email: neobyteid@gmail.com
Classifier: Programming Language :: Python :: 3
Classifier: License :: OSI Approved :: MIT License
Classifier: Operating System :: OS Independent
Requires-Python: >=3.6
